cpmpy/__init__.py
cpmpy/cli.py
cpmpy/exceptions.py
cpmpy/model.py
cpmpy/expressions/__init__.py
cpmpy/expressions/core.py
cpmpy/expressions/globalconstraints.py
cpmpy/expressions/globalfunctions.py
cpmpy/expressions/python_builtins.py
cpmpy/expressions/utils.py
cpmpy/expressions/variables.py
cpmpy/solvers/TEMPLATE.py
cpmpy/solvers/__init__.py
cpmpy/solvers/choco.py
cpmpy/solvers/cplex.py
cpmpy/solvers/cpo.py
cpmpy/solvers/exact.py
cpmpy/solvers/gcs.py
cpmpy/solvers/gurobi.py
cpmpy/solvers/hexaly.py
cpmpy/solvers/minizinc.py
cpmpy/solvers/ortools.py
cpmpy/solvers/pindakaas.py
cpmpy/solvers/pumpkin.py
cpmpy/solvers/pysat.py
cpmpy/solvers/pysdd.py
cpmpy/solvers/rc2.py
cpmpy/solvers/solver_interface.py
cpmpy/solvers/utils.py
cpmpy/solvers/z3.py
cpmpy/tools/__init__.py
cpmpy/tools/dimacs.py
cpmpy/tools/maximal_propagate.py
cpmpy/tools/mus.py
cpmpy/tools/tune_solver.py
cpmpy/tools/explain/__init__.py
cpmpy/tools/explain/marco.py
cpmpy/tools/explain/mcs.py
cpmpy/tools/explain/mss.py
cpmpy/tools/explain/mus.py
cpmpy/tools/explain/utils.py
cpmpy/tools/xcsp3/__init__.py
cpmpy/tools/xcsp3/analyze.py
cpmpy/tools/xcsp3/benchmark.py
cpmpy/tools/xcsp3/dataset.py
cpmpy/tools/xcsp3/globals.py
cpmpy/tools/xcsp3/parser_callbacks.py
cpmpy/tools/xcsp3/xcsp3_cpmpy.py
cpmpy/transformations/__init__.py
cpmpy/transformations/comparison.py
cpmpy/transformations/decompose_global.py
cpmpy/transformations/flatten_model.py
cpmpy/transformations/get_variables.py
cpmpy/transformations/int2bool.py
cpmpy/transformations/linearize.py
cpmpy/transformations/negation.py
cpmpy/transformations/normalize.py
cpmpy/transformations/reification.py
cpmpy/transformations/safening.py
cpmpy/transformations/to_cnf.py
cpmpy-0.10.0.dist-info/licenses/LICENSE
cpmpy-0.10.0.dist-info/METADATA
cpmpy-0.10.0.dist-info/WHEEL
cpmpy-0.10.0.dist-info/entry_points.txt
cpmpy-0.10.0.dist-info/top_level.txt
cpmpy-0.10.0.dist-info/RECORD
