Metadata-Version: 2.4
Name: cpmpy
Version: 0.10.0
Summary: A numpy-based library for modeling constraint programming problems
Home-page: https://github.com/CPMpy/cpmpy
Author: Tias Guns
Author-email: tias.guns@kuleuven.be
License: Apache 2.0
Classifier: Programming Language :: Python :: 3 :: Only
Classifier: Programming Language :: Python :: 3.10
Classifier: Programming Language :: Python :: 3.11
Classifier: Programming Language :: Python :: 3.12
Classifier: Programming Language :: Python :: 3.13
Classifier: License :: OSI Approved :: Apache Software License
Classifier: Operating System :: OS Independent
Requires-Python: >=3.10
License-File: LICENSE
Requires-Dist: ortools!=9.10.*,!=9.11.*,!=9.9.*,<=9.14.6206,>=9.3.10497
Requires-Dist: numpy>=1.5
Requires-Dist: setuptools
Requires-Dist: packaging
Provides-Extra: ortools
Requires-Dist: ortools!=9.10.*,!=9.11.*,!=9.9.*,<=9.14.6206,>=9.3.10497; extra == "ortools"
Provides-Extra: z3
Requires-Dist: z3-solver<=4.15.4.0,>=4.8.15.0; extra == "z3"
Provides-Extra: choco
Requires-Dist: pychoco<=0.2.4,>=0.2.1; extra == "choco"
Provides-Extra: exact
Requires-Dist: exact<=2.2.1,>=2.1.0; extra == "exact"
Provides-Extra: minizinc
Requires-Dist: minizinc<=0.10.0,>=0.7.0; extra == "minizinc"
Provides-Extra: pysat
Requires-Dist: python-sat<=1.9.dev26,>=1.8.dev4; extra == "pysat"
Provides-Extra: gurobi
Requires-Dist: gurobipy<=13.0.0,>=11.0.0; extra == "gurobi"
Provides-Extra: pysdd
Requires-Dist: pysdd<=1.0.6,>=0.2.11; extra == "pysdd"
Provides-Extra: gcs
Requires-Dist: gcspy==0.1.9; extra == "gcs"
Provides-Extra: cpo
Requires-Dist: docplex<=2.31.254,>=2.28.240; extra == "cpo"
Provides-Extra: pumpkin
Requires-Dist: pumpkin-solver==0.2.2; extra == "pumpkin"
Provides-Extra: pindakaas
Requires-Dist: pindakaas<=0.3.0,>=0.2.1; extra == "pindakaas"
Provides-Extra: cplex
Requires-Dist: docplex<=2.31.254,>=2.28.240; extra == "cplex"
Requires-Dist: cplex<=22.1.2.0,>=20.1.0.4; extra == "cplex"
Provides-Extra: all
Requires-Dist: pychoco<=0.2.4,>=0.2.1; extra == "all"
Requires-Dist: z3-solver<=4.15.4.0,>=4.8.15.0; extra == "all"
Requires-Dist: pindakaas<=0.3.0,>=0.2.1; extra == "all"
Requires-Dist: pysdd<=1.0.6,>=0.2.11; extra == "all"
Requires-Dist: pumpkin-solver==0.2.2; extra == "all"
Requires-Dist: gurobipy<=13.0.0,>=11.0.0; extra == "all"
Requires-Dist: minizinc<=0.10.0,>=0.7.0; extra == "all"
Requires-Dist: exact<=2.2.1,>=2.1.0; extra == "all"
Requires-Dist: gcspy==0.1.9; extra == "all"
Requires-Dist: cplex<=22.1.2.0,>=20.1.0.4; extra == "all"
Requires-Dist: python-sat<=1.9.dev26,>=1.8.dev4; extra == "all"
Requires-Dist: docplex<=2.31.254,>=2.28.240; extra == "all"
Requires-Dist: ortools!=9.10.*,!=9.11.*,!=9.9.*,<=9.14.6206,>=9.3.10497; extra == "all"
Provides-Extra: xcsp3
Requires-Dist: pycsp3; extra == "xcsp3"
Requires-Dist: requests; extra == "xcsp3"
Requires-Dist: tqdm; extra == "xcsp3"
Requires-Dist: matplotlib; extra == "xcsp3"
Requires-Dist: psutil; extra == "xcsp3"
Requires-Dist: filelock; extra == "xcsp3"
Requires-Dist: gnureadline; platform_system != "Windows" and extra == "xcsp3"
Requires-Dist: pyreadline3; platform_system == "Windows" and extra == "xcsp3"
Provides-Extra: test
Requires-Dist: pytest; extra == "test"
Requires-Dist: pytest-timeout; extra == "test"
Provides-Extra: docs
Requires-Dist: sphinx>=5.3.0; extra == "docs"
Requires-Dist: sphinx_rtd_theme>=2.0.0; extra == "docs"
Requires-Dist: myst_parser; extra == "docs"
Requires-Dist: sphinx-automodapi; extra == "docs"
Requires-Dist: readthedocs-sphinx-search>=0.3.2; extra == "docs"
Dynamic: author
Dynamic: author-email
Dynamic: classifier
Dynamic: description
Dynamic: description-content-type
Dynamic: home-page
Dynamic: license
Dynamic: license-file
Dynamic: provides-extra
Dynamic: requires-dist
Dynamic: requires-python
Dynamic: summary
